autoqasm/__init__.py
autoqasm/api.py
autoqasm/constants.py
autoqasm/errors.py
autoqasm/reserved_keywords.py
autoqasm/converters/__init__.py
autoqasm/converters/arithmetic.py
autoqasm/converters/assignments.py
autoqasm/converters/break_statements.py
autoqasm/converters/comparisons.py
autoqasm/converters/return_statements.py
autoqasm/converters/typecast.py
autoqasm/instructions/__init__.py
autoqasm/instructions/gates.py
autoqasm/instructions/instructions.py
autoqasm/instructions/measurements.py
autoqasm/instructions/qubits.py
autoqasm/operators/__init__.py
autoqasm/operators/arithmetic.py
autoqasm/operators/assignments.py
autoqasm/operators/comparisons.py
autoqasm/operators/conditional_expressions.py
autoqasm/operators/control_flow.py
autoqasm/operators/data_structures.py
autoqasm/operators/exceptions.py
autoqasm/operators/logical.py
autoqasm/operators/return_statements.py
autoqasm/operators/slices.py
autoqasm/operators/typecast.py
autoqasm/operators/utils.py
autoqasm/program/__init__.py
autoqasm/program/gate_calibrations.py
autoqasm/program/pragmas.py
autoqasm/program/program.py
autoqasm/program/serialization_properties.py
autoqasm/pulse/__init__.py
autoqasm/pulse/pulse.py
autoqasm/simulator/__init__.py
autoqasm/simulator/conversion.py
autoqasm/simulator/linalg_utils.py
autoqasm/simulator/native_interpreter.py
autoqasm/simulator/program_context.py
autoqasm/simulator/simulation.py
autoqasm/simulator/simulator.py
autoqasm/transpiler/__init__.py
autoqasm/transpiler/transpiler.py
autoqasm/types/__init__.py
autoqasm/types/conversions.py
autoqasm/types/types.py
autoqasm-0.2.0.dist-info/licenses/LICENSE
autoqasm-0.2.0.dist-info/licenses/NOTICE
autoqasm-0.2.0.dist-info/METADATA
autoqasm-0.2.0.dist-info/WHEEL
autoqasm-0.2.0.dist-info/entry_points.txt
autoqasm-0.2.0.dist-info/top_level.txt
autoqasm-0.2.0.dist-info/RECORD
