Metadata-Version: 2.4
Name: autoqasm
Version: 0.2.0
Summary: Python-native programming library for developing quantum programs
Home-page: https://github.com/amazon-braket/autoqasm
Author: Amazon Web Services
License: Apache License 2.0
Keywords: Amazon AWS Braket Quantum
Classifier: Development Status :: 5 - Production/Stable
Classifier: Intended Audience :: Developers
Classifier: Intended Audience :: Education
Classifier: Intended Audience :: Science/Research
Classifier: Natural Language :: English
Classifier: License :: OSI Approved :: Apache Software License
Classifier: Programming Language :: Python
Classifier: Programming Language :: Python :: 3.10
Classifier: Programming Language :: Python :: 3.11
Classifier: Programming Language :: Python :: 3.12
Classifier: Programming Language :: Python :: 3.13
Requires-Python: >= 3.10
License-File: LICENSE
License-File: NOTICE
Requires-Dist: amazon-braket-sdk>=1.89.1
Requires-Dist: amazon-braket-default-simulator>=1.23.2
Requires-Dist: oqpy~=0.3.5
Requires-Dist: diastatic-malt
Requires-Dist: numpy
Requires-Dist: openpulse
Requires-Dist: openqasm3
Requires-Dist: sympy
Requires-Dist: astunparse
Requires-Dist: gast
Requires-Dist: termcolor
Requires-Dist: openqasm_pygments
Provides-Extra: test
Requires-Dist: botocore; extra == "test"
Requires-Dist: jsonschema==3.2.0; extra == "test"
Requires-Dist: pre-commit; extra == "test"
Requires-Dist: pylint; extra == "test"
Requires-Dist: pytest; extra == "test"
Requires-Dist: pytest-cov; extra == "test"
Requires-Dist: pytest-rerunfailures; extra == "test"
Requires-Dist: pytest-xdist[psutil]; extra == "test"
Requires-Dist: ruff; extra == "test"
Requires-Dist: sphinx; extra == "test"
Requires-Dist: sphinx-rtd-theme; extra == "test"
Requires-Dist: sphinxcontrib-apidoc; extra == "test"
Requires-Dist: tox; extra == "test"
Dynamic: author
Dynamic: classifier
Dynamic: description
Dynamic: description-content-type
Dynamic: home-page
Dynamic: keywords
Dynamic: license
Dynamic: license-file
Dynamic: provides-extra
Dynamic: requires-dist
Dynamic: requires-python
Dynamic: summary
